YPC/vsrc/RegisterFile.v
module RegisterFile #(ADDR_WIDTH = 5, DATA_WIDTH = 32) (
  input clk,
  input [DATA_WIDTH-1:0] wdata,
  input [ADDR_WIDTH-1:0] waddr,
  input wen,
  output reg [DATA_WIDTH-1:0] rdata
);

  reg [DATA_WIDTH-1:0] rf [2**ADDR_WIDTH-1:0];

  // 初始化块，将所有寄存器的初始值设为 0
  initial begin
    integer i;
    for (i = 0; i < 2**ADDR_WIDTH; i = i + 1) begin
      rf[i] = 32'h00000000;
    end
  end

  always @(posedge clk) begin
    if (wen) begin
      if (waddr != 0) // Check if address is not 0
        rf[waddr] <= wdata;
    end
    rdata <= (waddr == 0) ? 32'h00000000 : rf[waddr]; // Output 0 for address 0
  end

endmodule

YPC/vsrc/EXU.v
module EXU #(DATA_WIDTH = 32) (
  input clk,
  input rst,
  input [31:0] immI,
  input [4:0] rd, rs1,
  input [6:0] opcode7,
  input [2:0] opcode3,
  output reg [31:0] wdata,
  output reg wen 
);

  // 寄存器文件模块
  RegisterFile regfile (
    .clk(clk),
    .wdata(wdata),
    .waddr(rs1),
    .wen(wen),
    .rdata(rs1_value)
  );

  reg [31:0] rs1_value; // 从寄存器文件中读取的rs1值

  always @(posedge clk) begin
    if (rst) begin
      wen <= 0;
    end
    else begin
      // 从寄存器文件中读取rs1的值
      rs1_value <= regfile.rdata;

      case (opcode3)
        3'b000: begin // ADDI
          wen <= 1;
          wdata <= rs1_value + immI;
        end
        // 添加其他指令的处理
        default: begin
          wen <= 0;
        end
      endcase
    end
  end
  
endmodule

YPC/vsrc/IDU.v
module IDU #(DATA_WIDTH = 32) (
  input clk,
  input rst,
  input [DATA_WIDTH-1:0] inst,
  output reg [31:0]   imm     ,
  output reg [4:0]    rd, rs1  ,
  output reg [6:0]    opcode7  ,
  output reg [2:0]    opcode3  
);

  always @(posedge clk) begin
    if (rst) begin
      imm     <=   0;
      rd      <=   0;
      rs1     <=   0;
      opcode7 <=   0;
      opcode3 <=   0;
    end
    else begin
      imm     <=   {{21{inst[31]}}, inst[30:20]};
      rd      <=   inst[11:7];
      rs1     <=   inst[19:15];
      opcode7 <=   inst[6:0];
      opcode3 <=   inst[14:12];
    end
  end
endmodule

YPC/vsrc/top.v
module top (
  input clk,
  input rst,
  input [31:0] inst,
  output reg [31:0] out,
  output reg [31:0] pc // 添加一个输出端口
);
  reg  [31:0]   pc_internal;
  wire [31:0]   imm;
  wire [4:0]    rd, rs1;
  wire [6:0]    opcode7;
  wire [2:0]    opcode3;
  wire [31:0]   wdata;
  wire          wen;

  // 将内部 pc 与外部 pc 同步
  always @(posedge clk) begin
    pc_internal <= pc;
  end

  always @(posedge clk) begin
    if(rst) begin
      pc_internal <= 32'h80000000;
    end
    else begin
      pc_internal <= pc_internal + 4;
    end
  end

  // 将内部 pc 输出到外部 pc
  assign pc = pc_internal;

  // IFU ifu (
  //   .clk         (clk),
  //   .rst         (rst),
  //   .pc          (pc_n)
  // );

  IDU idu (
    .clk         (clk),
    .rst         (rst),
    .inst        (inst),
    .imm         (imm),
    .rd          (rd),
    .rs1         (rs1),
    .opcode7     (opcode7),
    .opcode3     (opcode3)
  );

  EXU exu(
    .clk         (clk),
    .rst         (rst),
    .immI        (imm),
    .rd          (rd),
    .rs1         (rs1),
    .opcode7     (opcode7),
    .opcode3     (opcode3),
    .wdata       (wdata),
    .wen         (wen)
  );
  
endmodule

YPC/waveform.vcd
$version Generated by VerilatedVcd $end
$timescale 1ps $end

 $scope module TOP $end
  $var wire  1 M clk $end
  $var wire 32 O inst [31:0] $end
  $var wire 32 P out [31:0] $end
  $var wire 32 Q pc [31:0] $end
  $var wire  1 N rst $end
  $scope module top $end
   $var wire  1 M clk $end
   $var wire 32 % imm [31:0] $end
   $var wire 32 O inst [31:0] $end
   $var wire  3 ) opcode3 [2:0] $end
   $var wire  7 ( opcode7 [6:0] $end
   $var wire 32 P out [31:0] $end
   $var wire 32 Q pc [31:0] $end
   $var wire 32 $ pc_internal [31:0] $end
   $var wire  5 & rd [4:0] $end
   $var wire  5 ' rs1 [4:0] $end
   $var wire  1 N rst $end
   $var wire 32 * wdata [31:0] $end
   $var wire  1 + wen $end
   $scope module exu $end
    $var wire 32 R DATA_WIDTH [31:0] $end
    $var wire  1 M clk $end
    $var wire 32 % immI [31:0] $end
    $var wire  3 ) opcode3 [2:0] $end
    $var wire  7 ( opcode7 [6:0] $end
    $var wire  5 & rd [4:0] $end
    $var wire  5 ' rs1 [4:0] $end
    $var wire 32 , rs1_value [31:0] $end
    $var wire  1 N rst $end
    $var wire 32 * wdata [31:0] $end
    $var wire  1 + wen $end
    $scope module regfile $end
     $var wire 32 S ADDR_WIDTH [31:0] $end
     $var wire 32 R DATA_WIDTH [31:0] $end
     $var wire  1 M clk $end
     $var wire 32 , rdata [31:0] $end
     $var wire 32 - rf[0] [31:0] $end
     $var wire 32 7 rf[10] [31:0] $end
     $var wire 32 8 rf[11] [31:0] $end
     $var wire 32 9 rf[12] [31:0] $end
     $var wire 32 : rf[13] [31:0] $end
     $var wire 32 ; rf[14] [31:0] $end
     $var wire 32 < rf[15] [31:0] $end
     $var wire 32 = rf[16] [31:0] $end
     $var wire 32 > rf[17] [31:0] $end
     $var wire 32 ? rf[18] [31:0] $end
     $var wire 32 @ rf[19] [31:0] $end
     $var wire 32 . rf[1] [31:0] $end
     $var wire 32 A rf[20] [31:0] $end
     $var wire 32 B rf[21] [31:0] $end
     $var wire 32 C rf[22] [31:0] $end
     $var wire 32 D rf[23] [31:0] $end
     $var wire 32 E rf[24] [31:0] $end
     $var wire 32 F rf[25] [31:0] $end
     $var wire 32 G rf[26] [31:0] $end
     $var wire 32 H rf[27] [31:0] $end
     $var wire 32 I rf[28] [31:0] $end
     $var wire 32 J rf[29] [31:0] $end
     $var wire 32 / rf[2] [31:0] $end
     $var wire 32 K rf[30] [31:0] $end
     $var wire 32 L rf[31] [31:0] $end
     $var wire 32 0 rf[3] [31:0] $end
     $var wire 32 1 rf[4] [31:0] $end
     $var wire 32 2 rf[5] [31:0] $end
     $var wire 32 3 rf[6] [31:0] $end
     $var wire 32 4 rf[7] [31:0] $end
     $var wire 32 5 rf[8] [31:0] $end
     $var wire 32 6 rf[9] [31:0] $end
     $var wire  5 ' waddr [4:0] $end
     $var wire 32 * wdata [31:0] $end
     $var wire  1 + wen $end
     $scope module unnamedblk1 $end
      $var wire 32 # i [31:0] $end
     $upscope $end
    $upscope $end
   $upscope $end
   $scope module idu $end
    $var wire 32 R DATA_WIDTH [31:0] $end
    $var wire  1 M clk $end
    $var wire 32 % imm [31:0] $end
    $var wire 32 O inst [31:0] $end
    $var wire  3 ) opcode3 [2:0] $end
    $var wire  7 ( opcode7 [6:0] $end
    $var wire  5 & rd [4:0] $end
    $var wire  5 ' rs1 [4:0] $end
    $var wire  1 N rst $end
   $upscope $end
  $upscope $end
 $upscope $end
$enddefinitions $end


#0
b00000000000000000000000000100000 #
b00000000000000000000000000000000 $
b00000000000000000000000000000000 %
b00000 &
b00000 '
b0000000 (
b000 )
b00000000000000000000000000000000 *
0+
b00000000000000000000000000000000 ,
b00000000000000000000000000000000 -
b00000000000000000000000000000000 .
b00000000000000000000000000000000 /
b00000000000000000000000000000000 0
b00000000000000000000000000000000 1
b00000000000000000000000000000000 2
b00000000000000000000000000000000 3
b00000000000000000000000000000000 4
b00000000000000000000000000000000 5
b00000000000000000000000000000000 6
b00000000000000000000000000000000 7
b00000000000000000000000000000000 8
b00000000000000000000000000000000 9
b00000000000000000000000000000000 :
b00000000000000000000000000000000 ;
b00000000000000000000000000000000 <
b00000000000000000000000000000000 =
b00000000000000000000000000000000 >
b00000000000000000000000000000000 ?
b00000000000000000000000000000000 @
b00000000000000000000000000000000 A
b00000000000000000000000000000000 B
b00000000000000000000000000000000 C
b00000000000000000000000000000000 D
b00000000000000000000000000000000 E
b00000000000000000000000000000000 F
b00000000000000000000000000000000 G
b00000000000000000000000000000000 H
b00000000000000000000000000000000 I
b00000000000000000000000000000000 J
b00000000000000000000000000000000 K
b00000000000000000000000000000000 L
1M
0N
b00100110000000001000001010001010 O
b00000000000000000000000000000000 P
b00000000000000000000000000000000 Q
b00000000000000000000000000100000 R
b00000000000000000000000000000101 S
#1
0M
#2
b00000000000000000000000000000100 $
b00000000000000000000001001100000 %
b00101 &
b00001 '
b0001010 (
1+
1M
b00000000000000000000000000000100 Q
#3
0M
b00000000000000000000000000000000 O
#4
b00000000000000000000000000001000 $
b00000000000000000000000000000000 %
b00000 &
b00000 '
b0000000 (
b00000000000000000000001001100000 *
1M
b00000000000000000000000000001000 Q
#5
0M
#6
b00000000000000000000000000001100 $
b00000000000000000000000000000000 *
1M
b00000000000000000000000000001100 Q
#7
0M
#8
b00000000000000000000000000010000 $
1M
b00000000000000000000000000010000 Q
#9
0M
#10
b00000000000000000000000000010100 $
1M
b00000000000000000000000000010100 Q
#11
0M
#12
b00000000000000000000000000011000 $
1M
b00000000000000000000000000011000 Q
#13
0M
#14
b00000000000000000000000000011100 $
1M
b00000000000000000000000000011100 Q
#15
0M
#16
b00000000000000000000000000100000 $
1M
b00000000000000000000000000100000 Q
#17
0M
#18
b00000000000000000000000000100100 $
1M
b00000000000000000000000000100100 Q
